armulator/__init__.py
armulator/armv6/__init__.py
armulator/armv6/address_descriptor.py
armulator/armv6/arm_configurations.json
armulator/armv6/arm_exceptions.py
armulator/armv6/arm_v6.py
armulator/armv6/bits_ops.py
armulator/armv6/configurations.py
armulator/armv6/enums.py
armulator/armv6/full_address.py
armulator/armv6/memory_attributes.py
armulator/armv6/memory_controller_hub.py
armulator/armv6/memory_types.py
armulator/armv6/permissions.py
armulator/armv6/registers.py
armulator/armv6/shift.py
armulator/armv6/tlb_record.py
armulator/armv6/all_registers/__init__.py
armulator/armv6/all_registers/abstract_register.py
armulator/armv6/all_registers/cpacr.py
armulator/armv6/all_registers/cpsr.py
armulator/armv6/all_registers/dacr.py
armulator/armv6/all_registers/dbgdidr.py
armulator/armv6/all_registers/dfsr.py
armulator/armv6/all_registers/fcseidr.py
armulator/armv6/all_registers/fpexc.py
armulator/armv6/all_registers/hcptr.py
armulator/armv6/all_registers/hcr.py
armulator/armv6/all_registers/hdcr.py
armulator/armv6/all_registers/hpfar.py
armulator/armv6/all_registers/hsctlr.py
armulator/armv6/all_registers/hsr.py
armulator/armv6/all_registers/hstr.py
armulator/armv6/all_registers/htcr.py
armulator/armv6/all_registers/id_pfr1.py
armulator/armv6/all_registers/jmcr.py
armulator/armv6/all_registers/midr.py
armulator/armv6/all_registers/mpuir.py
armulator/armv6/all_registers/nmrr.py
armulator/armv6/all_registers/nsacr.py
armulator/armv6/all_registers/pmcr.py
armulator/armv6/all_registers/prrr.py
armulator/armv6/all_registers/racr.py
armulator/armv6/all_registers/rgnr.py
armulator/armv6/all_registers/rsr.py
armulator/armv6/all_registers/scr.py
armulator/armv6/all_registers/sctlr.py
armulator/armv6/all_registers/sder.py
armulator/armv6/all_registers/sunavcr.py
armulator/armv6/all_registers/teecr.py
armulator/armv6/all_registers/ttbcr.py
armulator/armv6/all_registers/vbar.py
armulator/armv6/all_registers/vtcr.py
armulator/armv6/opcodes/__init__.py
armulator-1.1.3.dist-info/LICENSE
armulator-1.1.3.dist-info/METADATA
armulator-1.1.3.dist-info/WHEEL
armulator-1.1.3.dist-info/top_level.txt
armulator-1.1.3.dist-info/RECORD
