Metadata-Version: 2.1
Name: armulator
Version: 1.1.3
Summary: A pure Python ARM processor emulator
Home-page: https://github.com/matan1008/armulator
Author: Matan Perelman
Author-email: matan1008@gmail.com
License: MIT
Keywords: arm emulator
Classifier: Programming Language :: Python :: 3.6
Classifier: Programming Language :: Python :: 3.7
Classifier: Programming Language :: Python :: 3.8
Classifier: Programming Language :: Python :: 3.9
Classifier: Programming Language :: Python :: 3.10
Classifier: Programming Language :: Python :: 3.11
License-File: LICENSE
